lethe/__init__.py
lethe/algo.py
lethe/eval.py
lethe/verify.py
lethe_ml-0.1.1.dist-info/METADATA
lethe_ml-0.1.1.dist-info/WHEEL
lethe_ml-0.1.1.dist-info/entry_points.txt
lethe_ml-0.1.1.dist-info/top_level.txt
lethe_ml-0.1.1.dist-info/RECORD
