Metadata-Version: 2.4
Name: lethe-ml
Version: 0.1.1
Summary: Lethe is a comprehensive Python library for machine unlearning - the process of selectively removing the influence of specific training data from machine learning models.
Author-email: Khushiyant <khushiyant2002@gmail.com>
Requires-Python: >=3.12
Requires-Dist: pandas>=2.3.2
Requires-Dist: pydantic>=2.11.7
Requires-Dist: scikit-learn>=1.7.1
Requires-Dist: seaborn>=0.13.2
